fds/__init__.py
fds/analyticsapi/__init__.py
fds/analyticsapi/engines/__init__.py
fds/analyticsapi/engines/api_client.py
fds/analyticsapi/engines/configuration.py
fds/analyticsapi/engines/exceptions.py
fds/analyticsapi/engines/model_utils.py
fds/analyticsapi/engines/rest.py
fds/analyticsapi/engines/api/__init__.py
fds/analyticsapi/engines/api/accounts_api.py
fds/analyticsapi/engines/api/afi_optimizer_api.py
fds/analyticsapi/engines/api/axp_optimizer_api.py
fds/analyticsapi/engines/api/benchmarks_api.py
fds/analyticsapi/engines/api/bpm_optimizer_api.py
fds/analyticsapi/engines/api/column_statistics_api.py
fds/analyticsapi/engines/api/columns_api.py
fds/analyticsapi/engines/api/components_api.py
fds/analyticsapi/engines/api/configurations_api.py
fds/analyticsapi/engines/api/currencies_api.py
fds/analyticsapi/engines/api/dates_api.py
fds/analyticsapi/engines/api/discount_curves_api.py
fds/analyticsapi/engines/api/documents_api.py
fds/analyticsapi/engines/api/fi_calculations_api.py
fds/analyticsapi/engines/api/fiab_calculations_api.py
fds/analyticsapi/engines/api/fpo_optimizer_api.py
fds/analyticsapi/engines/api/frequencies_api.py
fds/analyticsapi/engines/api/groups_api.py
fds/analyticsapi/engines/api/linked_pa_templates_api.py
fds/analyticsapi/engines/api/npo_optimizer_api.py
fds/analyticsapi/engines/api/pa_calculations_api.py
fds/analyticsapi/engines/api/pricing_sources_api.py
fds/analyticsapi/engines/api/pub_calculations_api.py
fds/analyticsapi/engines/api/quant_calculations_api.py
fds/analyticsapi/engines/api/spar_calculations_api.py
fds/analyticsapi/engines/api/strategy_documents_api.py
fds/analyticsapi/engines/api/templated_pa_components_api.py
fds/analyticsapi/engines/api/unlinked_pa_templates_api.py
fds/analyticsapi/engines/api/vault_calculations_api.py
fds/analyticsapi/engines/apis/__init__.py
fds/analyticsapi/engines/model/__init__.py
fds/analyticsapi/engines/model/account_directories.py
fds/analyticsapi/engines/model/account_directories_root.py
fds_analyticsapi_engines-6.1.1.dist-info/METADATA
fds_analyticsapi_engines-6.1.1.dist-info/WHEEL
fds_analyticsapi_engines-6.1.1.dist-info/top_level.txt
fds_analyticsapi_engines-6.1.1.dist-info/RECORD
