Metadata-Version: 2.4
Name: fds_analyticsapi_engines
Version: 6.1.1
Summary: Engines API
Home-page: https://github.com/factset/analyticsapi-engines-python-sdk
Author: FactSet Research Systems
Author-email: api@factset.com
License: Apache License, Version 2.0
Keywords: OpenAPI,OpenAPI-Generator,Engines API
Requires-Python: >=3.6
Requires-Dist: urllib3>=1.25.3
Requires-Dist: python-dateutil
Requires-Dist: fds.protobuf.stach.extensions<2.0.0
Dynamic: author
Dynamic: author-email
Dynamic: description
Dynamic: home-page
Dynamic: keywords
Dynamic: license
Dynamic: requires-dist
Dynamic: requires-python
Dynamic: summary
